{
  "name": "The Honorable General",
  "steps": [
    {"type": "travel", "name": "Travel to Jokanur Diggings outpost", "target_map_id": 491},
    {"type": "auto_path", "name": "To Digmaster Gatah", "points": [[3294, 1641], [2922, 2126]]},
    {"type": "dialog", "id": "0x827901", "npc": "DIGMASTER_GATAH", "name": "Dialog - Digmaster Gatah"},
    {"type": "travel", "name": "Travel to Sunspear Great Hall", "target_map_id": 431},
    {"type": "travel", "name": "Travel to The Astralarium", "target_map_id": 502},
    {"type": "load_party", "name": "Load Party", "max_heroes": 4, "use_priority": true},
    {"type": "auto_path", "name": "To Exit", "points": [[-4255, 729]]},
    {"type": "exit_map", "name": "Leave The Astralarium", "point": [-4647, 156], "target_map_id": 483},
    {"type": "auto_path", "name": "Path", "points": [[16916, -4019], [17288, -5024]]},
    {"type": "wait", "ms": 15000},
    {"type": "dialogs", "id": ["0x827904", "0x84"], "npc": "GENERAL_MORGAHN", "name": "Dialog - General Morgahn"},
    {"type": "auto_path", "name": "To General Morgahn", "points": [[18490, -5864], [17312, -5081]]},
    {"type": "dialog", "id": "0x827904", "npc": "GENERAL_MORGAHN", "name": "Dialog - General Morgahn"},
    {"type": "travel", "name": "Travel to The Astralarium", "target_map_id": 502},
    {"type": "auto_path", "name": "To Emissary Dajmir", "points": [[-1743, 3698]]},
    {"type": "dialog", "id": "0x827907", "npc": "EMISSARY_DAJMIR", "name": "Dialog - Emissary Dajmir"}
  ]
}

